pytorch_rdc_net/__init__.py
pytorch_rdc_net/embedding_loss.py
pytorch_rdc_net/generic_model.py
pytorch_rdc_net/lovasz_losses.py
pytorch_rdc_net/matching.py
pytorch_rdc_net/stacked_dilated_conv.py
pytorch_rdc_net/utils.py
pytorch_rdc_net-0.1.0.dist-info/METADATA
pytorch_rdc_net-0.1.0.dist-info/WHEEL
pytorch_rdc_net-0.1.0.dist-info/licenses/LICENSE
pytorch_rdc_net-0.1.0.dist-info/RECORD
